icon_writer/__init__.py
icon_writer/fonts/OpenSans-Bold.ttf
icon_writer-0.0.4.dist-info/METADATA
icon_writer-0.0.4.dist-info/WHEEL
icon_writer-0.0.4.dist-info/licenses/LICENSE
icon_writer-0.0.4.dist-info/RECORD
