Metadata-Version: 2.1
Name: icon_writer
Version: 0.0.4
Summary: A tiny package for writing Mac OS X text-only dock icons
Project-URL: Homepage, https://github.com/pamelafox/dock-icons
Project-URL: Bug Tracker, https://github.com/pamelafox/dock-icons/issues
Author-email: Pamela Fox <pamela.fox@gmail.com>
License: MIT License
License-File: LICENSE
Classifier: License :: OSI Approved :: MIT License
Classifier: Operating System :: OS Independent
Classifier: Programming Language :: Python :: 3
Requires-Python: >=3.7
Requires-Dist: pillow~=9.2
